mlbackend/__init__.py
mlbackend/__main__.py
mlbackend/mlrestapp.py
mlbackend/project.py
mlbackend/hooks/__init__.py
mlbackend/hooks/sqlite_hook.py
mlbackend-0.0.3.dist-info/METADATA
mlbackend-0.0.3.dist-info/WHEEL
mlbackend-0.0.3.dist-info/top_level.txt
mlbackend-0.0.3.dist-info/RECORD
